setup.py
dsnd_probability_wes/Binomialdistribution.py
dsnd_probability_wes/Gaussiandistribution.py
dsnd_probability_wes/Generaldistribution.py
dsnd_probability_wes/__init__.py
dsnd_probability_wes.egg-info/PKG-INFO
dsnd_probability_wes.egg-info/SOURCES.txt
dsnd_probability_wes.egg-info/dependency_links.txt
dsnd_probability_wes.egg-info/not-zip-safe
dsnd_probability_wes.egg-info/top_level.txt