Metadata-Version: 1.0
Name: dsnd-probability-wes
Version: 0.2
Summary: Gaussian and Binomial distributions
Home-page: UNKNOWN
Author: Wesley Siow
Author-email: myemail@acompany.com
License: UNKNOWN
Platform: UNKNOWN
